{
  "$fuchsia/rbe": {
    "instance": "projects/rbe-fuchsia-prod/instances/default"
  },
  "checkout_attributes": [
    "vulkan-cts"
  ],
  "fint_params_path": "integration/infra/config/generated/fuchsia/fint_params/prod/vulkan-cts-arm64-release-prebuilt.textproto",
  "manifest": "flower",
  "no_python2": true,
  "package_archive_cipd_path": "fuchsia/third_party/vulkan-cts/${name}/${cpu}_${api_level}",
  "recipe": "publish_build_artifacts",
  "remote": "https://fuchsia.googlesource.com/integration"
}
